manhattan_remote/__init__.py
manhattan_remote/client.py
manhattan_remote/exceptions.py
manhattan_remote/keys.py
manhattan_remote/py.typed
manhattan_remote-0.1.0.dist-info/WHEEL
manhattan_remote-0.1.0.dist-info/METADATA
manhattan_remote-0.1.0.dist-info/RECORD
