Metadata-Version: 2.3
Name: manhattan-remote
Version: 0.1.0
Summary: Async Python library for controlling Manhattan T4/T4R TV Box via HTTP
Keywords: manhattan,tv,remote,t4,t4r,async
Author: foxy82
Author-email: foxy82 <foxy82.github@gmail.com>
License: MIT
Requires-Dist: aiohttp>=3.8.0
Requires-Dist: pytest>=7.0.0 ; extra == 'dev'
Requires-Dist: pytest-asyncio>=0.21.0 ; extra == 'dev'
Requires-Dist: pytest-cov>=4.0.0 ; extra == 'dev'
Requires-Dist: black>=23.0.0 ; extra == 'dev'
Requires-Dist: ruff>=0.1.0 ; extra == 'dev'
Requires-Dist: mypy>=1.0.0 ; extra == 'dev'
Requires-Python: >=3.11
Project-URL: Homepage, https://github.com/designer-living/manhattan-remote
Project-URL: Issues, https://github.com/designer-living/manhattan-remote/issues
Project-URL: Repository, https://github.com/designer-living/manhattan-remote
Provides-Extra: dev
